{
"type": "FeatureCollection",
"name": "ky-5",
"crs": { "type": "name", "properties": { "name": "urn:ogc:def:crs:OGC:1.3:CRS84" } },
"features": [
{ "type": "Feature", "properties": { "len": 3140, "sum": 9140563, "avg": 2911, "min": 1, "max": 14570 }, "geometry": { "type": "Point", "coordinates": [ -89.90444, 36.59022 ] } },
{ "type": "Feature", "properties": { "len": 1780401, "sum": 5594504032, "avg": 3142, "min": 1, "max": 54321 }, "geometry": { "type": "Point", "coordinates": [ -86.15441, 38.76287 ] } },
{ "type": "Feature", "properties": { "len": 936542, "sum": 1701785873, "avg": 1817, "min": 1, "max": 94461 }, "geometry": { "type": "Point", "coordinates": [ -82.40444, 36.59022 ] } }
]
}
