{
"type": "FeatureCollection",
"name": "nj-0.5",
"crs": { "type": "name", "properties": { "name": "urn:ogc:def:crs:OGC:1.3:CRS84" } },
"features": [
{ "type": "Feature", "properties": { "len": 12169, "sum": 1953040, "avg": 160, "min": 1, "max": 1326 }, "geometry": { "type": "Point", "coordinates": [ -75.59295, 39.36256 ] } },
{ "type": "Feature", "properties": { "len": 12169, "sum": 1953040, "avg": 160, "min": 1, "max": 1326 }, "geometry": { "type": "Point", "coordinates": [ -75.59295, 39.79559 ] } },
{ "type": "Feature", "properties": { "len": 37886, "sum": 26742237, "avg": 705, "min": 1, "max": 13194 }, "geometry": { "type": "Point", "coordinates": [ -75.21795, 39.14605 ] } },
{ "type": "Feature", "properties": { "len": 232738, "sum": 120210192, "avg": 516, "min": 1, "max": 13194 }, "geometry": { "type": "Point", "coordinates": [ -75.21795, 39.57908 ] } },
{ "type": "Feature", "properties": { "len": 188389, "sum": 92418982, "avg": 490, "min": 1, "max": 8205 }, "geometry": { "type": "Point", "coordinates": [ -75.21795, 40.0121 ] } },
{ "type": "Feature", "properties": { "len": 20918, "sum": 8386389, "avg": 400, "min": 1, "max": 3952 }, "geometry": { "type": "Point", "coordinates": [ -75.21795, 40.44513 ] } },
{ "type": "Feature", "properties": { "len": 20964, "sum": 8388690, "avg": 400, "min": 1, "max": 3952 }, "geometry": { "type": "Point", "coordinates": [ -75.21795, 40.87816 ] } },
{ "type": "Feature", "properties": { "len": 46, "sum": 2301, "avg": 50, "min": 7, "max": 141 }, "geometry": { "type": "Point", "coordinates": [ -75.21795, 41.31119 ] } },
{ "type": "Feature", "properties": { "len": 149442, "sum": 167586339, "avg": 1121, "min": 1, "max": 12140 }, "geometry": { "type": "Point", "coordinates": [ -74.84295, 38.92953 ] } },
{ "type": "Feature", "properties": { "len": 190118, "sum": 260770224, "avg": 1371, "min": 1, "max": 12140 }, "geometry": { "type": "Point", "coordinates": [ -74.84295, 39.36256 ] } },
{ "type": "Feature", "properties": { "len": 312654, "sum": 227748336, "avg": 728, "min": 1, "max": 28772 }, "geometry": { "type": "Point", "coordinates": [ -74.84295, 39.79559 ] } },
{ "type": "Feature", "properties": { "len": 192642, "sum": 70271246, "avg": 364, "min": 1, "max": 28772 }, "geometry": { "type": "Point", "coordinates": [ -74.84295, 40.22862 ] } },
{ "type": "Feature", "properties": { "len": 221414, "sum": 44078886, "avg": 199, "min": 1, "max": 40546 }, "geometry": { "type": "Point", "coordinates": [ -74.84295, 40.66165 ] } },
{ "type": "Feature", "properties": { "len": 148083, "sum": 25334494, "avg": 171, "min": 1, "max": 40546 }, "geometry": { "type": "Point", "coordinates": [ -74.84295, 41.09468 ] } },
{ "type": "Feature", "properties": { "len": 103079, "sum": 90047988, "avg": 873, "min": 1, "max": 9803 }, "geometry": { "type": "Point", "coordinates": [ -74.46795, 39.14605 ] } },
{ "type": "Feature", "properties": { "len": 133219, "sum": 118813598, "avg": 891, "min": 1, "max": 9803 }, "geometry": { "type": "Point", "coordinates": [ -74.46795, 39.57908 ] } },
{ "type": "Feature", "properties": { "len": 213525, "sum": 62069236, "avg": 290, "min": 1, "max": 28772 }, "geometry": { "type": "Point", "coordinates": [ -74.46795, 40.0121 ] } },
{ "type": "Feature", "properties": { "len": 714897, "sum": 300923978, "avg": 420, "min": 1, "max": 32308 }, "geometry": { "type": "Point", "coordinates": [ -74.46795, 40.44513 ] } },
{ "type": "Feature", "properties": { "len": 689235, "sum": 215295686, "avg": 312, "min": 1, "max": 26180 }, "geometry": { "type": "Point", "coordinates": [ -74.46795, 40.87816 ] } },
{ "type": "Feature", "properties": { "len": 119453, "sum": 22022827, "avg": 184, "min": 1, "max": 9326 }, "geometry": { "type": "Point", "coordinates": [ -74.46795, 41.31119 ] } },
{ "type": "Feature", "properties": { "len": 15953, "sum": 16703351, "avg": 1047, "min": 1, "max": 23256 }, "geometry": { "type": "Point", "coordinates": [ -74.09295, 39.36256 ] } },
{ "type": "Feature", "properties": { "len": 275143, "sum": 170731622, "avg": 620, "min": 1, "max": 23256 }, "geometry": { "type": "Point", "coordinates": [ -74.09295, 39.79559 ] } },
{ "type": "Feature", "properties": { "len": 551048, "sum": 218613456, "avg": 396, "min": 1, "max": 20208 }, "geometry": { "type": "Point", "coordinates": [ -74.09295, 40.22862 ] } },
{ "type": "Feature", "properties": { "len": 1324524, "sum": 463665952, "avg": 350, "min": 1, "max": 9911 }, "geometry": { "type": "Point", "coordinates": [ -74.09295, 40.66165 ] } },
{ "type": "Feature", "properties": { "len": 871286, "sum": 324034856, "avg": 371, "min": 1, "max": 68306 }, "geometry": { "type": "Point", "coordinates": [ -74.09295, 41.09468 ] } }
]
}
