{
"type": "FeatureCollection",
"name": "nj-5",
"crs": { "type": "name", "properties": { "name": "urn:ogc:def:crs:OGC:1.3:CRS84" } },
"features": [
{ "type": "Feature", "properties": { "len": 3276354, "sum": 1209778430, "avg": 369, "min": 1, "max": 68306 }, "geometry": { "type": "Point", "coordinates": [ -75.89251, 39.03016 ] } }
]
}
