{
"type": "FeatureCollection",
"name": "data",
"crs": { "type": "name", "properties": { "name": "urn:ogc:def:crs:OGC:1.3:CRS84" } },
"features": [
{ "type": "Feature", "properties": { "len": 530364, "sum": 2601508751, "avg": 4905, "min": 1, "max": 83001 }, "geometry": { "type": "Point", "coordinates": [ -96.10764, 36.08708 ] } },
{ "type": "Feature", "properties": { "len": 530364, "sum": 2601508751, "avg": 4905, "min": 1, "max": 83001 }, "geometry": { "type": "Point", "coordinates": [ -96.10757, 40.43263 ] } },
{ "type": "Feature", "properties": { "len": 513076, "sum": 2297850200, "avg": 4478, "min": 1, "max": 65895 }, "geometry": { "type": "Point", "coordinates": [ -92.35761, 38.25962 ] } },
{ "type": "Feature", "properties": { "len": 166082, "sum": 452219974, "avg": 2722, "min": 1, "max": 42300 }, "geometry": { "type": "Point", "coordinates": [ -92.35753, 42.60617 ] } }
]
}
