{
"type": "FeatureCollection",
"name": "data",
"crs": { "type": "name", "properties": { "name": "urn:ogc:def:crs:OGC:1.3:CRS84" } },
"features": [
{ "type": "Feature", "properties": { "len": 29396, "sum": 67482047, "avg": 2295, "min": 1, "max": 99390 }, "geometry": { "type": "Point", "coordinates": [ -111.38974, 41.10413 ] } },
{ "type": "Feature", "properties": { "len": 102054, "sum": 119700326, "avg": 1172, "min": 1, "max": 64253 }, "geometry": { "type": "Point", "coordinates": [ -107.63969, 43.27785 ] } }
]
}
