{
"type": "FeatureCollection",
"name": "ms-1",
"crs": { "type": "name", "properties": { "name": "urn:ogc:def:crs:OGC:1.3:CRS84" } },
"features": [
{ "type": "Feature", "properties": { "len": 13543, "sum": 4955381, "avg": 365, "min": 1, "max": 3907 }, "geometry": { "type": "Point", "coordinates": [ -91.72167, 31.04299 ] } },
{ "type": "Feature", "properties": { "len": 13543, "sum": 4955381, "avg": 365, "min": 1, "max": 3907 }, "geometry": { "type": "Point", "coordinates": [ -91.72167, 31.90912 ] } },
{ "type": "Feature", "properties": { "len": 73, "sum": 213780, "avg": 2928, "min": 2, "max": 8168 }, "geometry": { "type": "Point", "coordinates": [ -90.97167, 30.60992 ] } },
{ "type": "Feature", "properties": { "len": 27439, "sum": 37727028, "avg": 1374, "min": 1, "max": 71058 }, "geometry": { "type": "Point", "coordinates": [ -90.97167, 31.47605 ] } },
{ "type": "Feature", "properties": { "len": 16114, "sum": 37484298, "avg": 2326, "min": 1, "max": 71058 }, "geometry": { "type": "Point", "coordinates": [ -90.97167, 32.34218 ] } },
{ "type": "Feature", "properties": { "len": 14132, "sum": 13530188, "avg": 957, "min": 1, "max": 51204 }, "geometry": { "type": "Point", "coordinates": [ -90.97167, 33.20832 ] } },
{ "type": "Feature", "properties": { "len": 12841, "sum": 16228993, "avg": 1263, "min": 1, "max": 98071 }, "geometry": { "type": "Point", "coordinates": [ -90.97167, 34.07445 ] } },
{ "type": "Feature", "properties": { "len": 965, "sum": 7706643, "avg": 7986, "min": 1, "max": 98071 }, "geometry": { "type": "Point", "coordinates": [ -90.97167, 34.94059 ] } },
{ "type": "Feature", "properties": { "len": 1553, "sum": 520917, "avg": 335, "min": 1, "max": 5815 }, "geometry": { "type": "Point", "coordinates": [ -90.22167, 30.17686 ] } },
{ "type": "Feature", "properties": { "len": 2925, "sum": 4931899, "avg": 1686, "min": 1, "max": 46137 }, "geometry": { "type": "Point", "coordinates": [ -90.22167, 31.04299 ] } },
{ "type": "Feature", "properties": { "len": 214217, "sum": 319085269, "avg": 1489, "min": 1, "max": 76303 }, "geometry": { "type": "Point", "coordinates": [ -90.22167, 31.90912 ] } },
{ "type": "Feature", "properties": { "len": 210729, "sum": 283676029, "avg": 1346, "min": 1, "max": 76303 }, "geometry": { "type": "Point", "coordinates": [ -90.22167, 32.77525 ] } },
{ "type": "Feature", "properties": { "len": 1372, "sum": 5347758, "avg": 3897, "min": 1, "max": 36577 }, "geometry": { "type": "Point", "coordinates": [ -90.22167, 33.64138 ] } },
{ "type": "Feature", "properties": { "len": 85575, "sum": 399819905, "avg": 4672, "min": 1, "max": 31130 }, "geometry": { "type": "Point", "coordinates": [ -90.22167, 34.50752 ] } },
{ "type": "Feature", "properties": { "len": 125534, "sum": 732244644, "avg": 5833, "min": 1, "max": 99120 }, "geometry": { "type": "Point", "coordinates": [ -89.47167, 30.60992 ] } },
{ "type": "Feature", "properties": { "len": 42143, "sum": 32842362, "avg": 779, "min": 1, "max": 32540 }, "geometry": { "type": "Point", "coordinates": [ -89.47167, 31.47605 ] } },
{ "type": "Feature", "properties": { "len": 26784, "sum": 29190474, "avg": 1089, "min": 1, "max": 39774 }, "geometry": { "type": "Point", "coordinates": [ -89.47167, 32.34218 ] } },
{ "type": "Feature", "properties": { "len": 16087, "sum": 41729467, "avg": 2593, "min": 1, "max": 39774 }, "geometry": { "type": "Point", "coordinates": [ -89.47167, 33.20832 ] } },
{ "type": "Feature", "properties": { "len": 11023, "sum": 17958221, "avg": 1629, "min": 1, "max": 25983 }, "geometry": { "type": "Point", "coordinates": [ -89.47167, 34.07445 ] } },
{ "type": "Feature", "properties": { "len": 26548, "sum": 190113168, "avg": 7161, "min": 1, "max": 15027 }, "geometry": { "type": "Point", "coordinates": [ -89.47167, 34.94059 ] } },
{ "type": "Feature", "properties": { "len": 303895, "sum": 1741111877, "avg": 5729, "min": 1, "max": 96498 }, "geometry": { "type": "Point", "coordinates": [ -88.72167, 30.17686 ] } },
{ "type": "Feature", "properties": { "len": 174872, "sum": 1037756363, "avg": 5934, "min": 1, "max": 84738 }, "geometry": { "type": "Point", "coordinates": [ -88.72167, 31.04299 ] } },
{ "type": "Feature", "properties": { "len": 6791, "sum": 14123878, "avg": 2079, "min": 3, "max": 51220 }, "geometry": { "type": "Point", "coordinates": [ -88.72167, 31.90912 ] } },
{ "type": "Feature", "properties": { "len": 11541, "sum": 24454718, "avg": 2118, "min": 1, "max": 51220 }, "geometry": { "type": "Point", "coordinates": [ -88.72167, 32.77525 ] } },
{ "type": "Feature", "properties": { "len": 23121, "sum": 47013594, "avg": 2033, "min": 1, "max": 31855 }, "geometry": { "type": "Point", "coordinates": [ -88.72167, 33.64138 ] } },
{ "type": "Feature", "properties": { "len": 25040, "sum": 28532708, "avg": 1139, "min": 1, "max": 31855 }, "geometry": { "type": "Point", "coordinates": [ -88.72167, 34.50752 ] } }
]
}
