{
"type": "FeatureCollection",
"name": "data",
"crs": { "type": "name", "properties": { "name": "urn:ogc:def:crs:OGC:1.3:CRS84" } },
"features": [
{ "type": "Feature", "properties": { "len": 458504, "sum": 3516081395, "avg": 7668, "min": 1, "max": 94900 }, "geometry": { "type": "Point", "coordinates": [ -115.14951, 31.40875 ] } },
{ "type": "Feature", "properties": { "len": 462803, "sum": 3524946865, "avg": 7616, "min": 1, "max": 94900 }, "geometry": { "type": "Point", "coordinates": [ -115.14946, 35.75258 ] } },
{ "type": "Feature", "properties": { "len": 3762623, "sum": 28616793729, "avg": 7605, "min": 1, "max": 99987 }, "geometry": { "type": "Point", "coordinates": [ -111.39949, 33.58049 ] } },
{ "type": "Feature", "properties": { "len": 346389, "sum": 1361904355, "avg": 3931, "min": 1, "max": 98940 }, "geometry": { "type": "Point", "coordinates": [ -111.39942, 37.92506 ] } }
]
}
