{
"type": "FeatureCollection",
"name": "sd-5",
"crs": { "type": "name", "properties": { "name": "urn:ogc:def:crs:OGC:1.3:CRS84" } },
"features": [
{ "type": "Feature", "properties": { "len": 108788, "sum": 672033005, "avg": 6177, "min": 1, "max": 66350 }, "geometry": { "type": "Point", "coordinates": [ -104.39052, 42.59489 ] } },
{ "type": "Feature", "properties": { "len": 53230, "sum": 443712637, "avg": 8335, "min": 1, "max": 57511 }, "geometry": { "type": "Point", "coordinates": [ -100.64047, 44.76904 ] } },
{ "type": "Feature", "properties": { "len": 362911, "sum": 2753318941, "avg": 7586, "min": 1, "max": 89891 }, "geometry": { "type": "Point", "coordinates": [ -96.89052, 42.59489 ] } }
]
}
