{
"type": "FeatureCollection",
"name": "mo-1",
"crs": { "type": "name", "properties": { "name": "urn:ogc:def:crs:OGC:1.3:CRS84" } },
"features": [
{ "type": "Feature", "properties": { "len": 8224, "sum": 39712607, "avg": 4828, "min": 1, "max": 24220 }, "geometry": { "type": "Point", "coordinates": [ -95.09137, 39.03084 ] } },
{ "type": "Feature", "properties": { "len": 8224, "sum": 39712607, "avg": 4828, "min": 1, "max": 24220 }, "geometry": { "type": "Point", "coordinates": [ -95.09137, 39.89699 ] } },
{ "type": "Feature", "properties": { "len": 53689, "sum": 196268067, "avg": 3655, "min": 1, "max": 31974 }, "geometry": { "type": "Point", "coordinates": [ -94.34137, 36.86547 ] } },
{ "type": "Feature", "properties": { "len": 49694, "sum": 197399251, "avg": 3972, "min": 1, "max": 31974 }, "geometry": { "type": "Point", "coordinates": [ -94.34137, 37.73162 ] } },
{ "type": "Feature", "properties": { "len": 515684, "sum": 2563387715, "avg": 4970, "min": 1, "max": 83001 }, "geometry": { "type": "Point", "coordinates": [ -94.34137, 38.59776 ] } },
{ "type": "Feature", "properties": { "len": 553209, "sum": 2806213019, "avg": 5072, "min": 1, "max": 83001 }, "geometry": { "type": "Point", "coordinates": [ -94.34137, 39.46392 ] } },
{ "type": "Feature", "properties": { "len": 89, "sum": 705270, "avg": 7924, "min": 300, "max": 14401 }, "geometry": { "type": "Point", "coordinates": [ -94.34137, 40.33007 ] } },
{ "type": "Feature", "properties": { "len": 3604, "sum": 5341563, "avg": 1482, "min": 1, "max": 12380 }, "geometry": { "type": "Point", "coordinates": [ -93.59137, 36.4324 ] } },
{ "type": "Feature", "properties": { "len": 3604, "sum": 5341563, "avg": 1482, "min": 1, "max": 12380 }, "geometry": { "type": "Point", "coordinates": [ -93.59137, 37.29854 ] } },
{ "type": "Feature", "properties": { "len": 1762, "sum": 6921973, "avg": 3928, "min": 100, "max": 43000 }, "geometry": { "type": "Point", "coordinates": [ -92.84137, 35.99933 ] } },
{ "type": "Feature", "properties": { "len": 22439, "sum": 35216146, "avg": 1569, "min": 1, "max": 43000 }, "geometry": { "type": "Point", "coordinates": [ -92.84137, 36.86547 ] } },
{ "type": "Feature", "properties": { "len": 31831, "sum": 88039209, "avg": 2765, "min": 1, "max": 19000 }, "geometry": { "type": "Point", "coordinates": [ -92.84137, 38.59776 ] } },
{ "type": "Feature", "properties": { "len": 31831, "sum": 88039209, "avg": 2765, "min": 1, "max": 19000 }, "geometry": { "type": "Point", "coordinates": [ -92.84137, 39.46392 ] } },
{ "type": "Feature", "properties": { "len": 49054, "sum": 150229098, "avg": 3062, "min": 1, "max": 43995 }, "geometry": { "type": "Point", "coordinates": [ -92.09137, 38.16469 ] } },
{ "type": "Feature", "properties": { "len": 161362, "sum": 448948701, "avg": 2782, "min": 1, "max": 42300 }, "geometry": { "type": "Point", "coordinates": [ -92.09137, 39.03084 ] } },
{ "type": "Feature", "properties": { "len": 2472, "sum": 7411482, "avg": 2998, "min": 1, "max": 24300 }, "geometry": { "type": "Point", "coordinates": [ -92.09137, 39.89699 ] } },
{ "type": "Feature", "properties": { "len": 1, "sum": 1344, "avg": 1344, "min": 1344, "max": 1344 }, "geometry": { "type": "Point", "coordinates": [ -91.34137, 36.86547 ] } },
{ "type": "Feature", "properties": { "len": 1502, "sum": 31373232, "avg": 20887, "min": 257, "max": 53237 }, "geometry": { "type": "Point", "coordinates": [ -91.34137, 37.73162 ] } },
{ "type": "Feature", "properties": { "len": 4464, "sum": 42988964, "avg": 9630, "min": 1, "max": 53237 }, "geometry": { "type": "Point", "coordinates": [ -91.34137, 38.59776 ] } },
{ "type": "Feature", "properties": { "len": 45, "sum": 52383, "avg": 1164, "min": 102, "max": 2378 }, "geometry": { "type": "Point", "coordinates": [ -91.34137, 39.46392 ] } },
{ "type": "Feature", "properties": { "len": 11713, "sum": 57058724, "avg": 4871, "min": 1, "max": 61229 }, "geometry": { "type": "Point", "coordinates": [ -90.59137, 37.29854 ] } },
{ "type": "Feature", "properties": { "len": 831305, "sum": 3242068386, "avg": 3899, "min": 1, "max": 51204 }, "geometry": { "type": "Point", "coordinates": [ -90.59137, 38.16469 ] } },
{ "type": "Feature", "properties": { "len": 844947, "sum": 3179925279, "avg": 3763, "min": 1, "max": 51204 }, "geometry": { "type": "Point", "coordinates": [ -90.59137, 39.03084 ] } },
{ "type": "Feature", "properties": { "len": 24752, "sum": 36984997, "avg": 1494, "min": 1, "max": 28814 }, "geometry": { "type": "Point", "coordinates": [ -89.84137, 36.86547 ] } },
{ "type": "Feature", "properties": { "len": 33678, "sum": 51189863, "avg": 1519, "min": 1, "max": 33480 }, "geometry": { "type": "Point", "coordinates": [ -89.84137, 37.73162 ] } },
{ "type": "Feature", "properties": { "len": 145123, "sum": 681059578, "avg": 4692, "min": 1, "max": 33480 }, "geometry": { "type": "Point", "coordinates": [ -89.84137, 38.59776 ] } }
]
}
