{
"type": "FeatureCollection",
"name": "data",
"crs": { "type": "name", "properties": { "name": "urn:ogc:def:crs:OGC:1.3:CRS84" } },
"features": [
{ "type": "Feature", "properties": { "len": 25339, "sum": 22676941, "avg": 894, "min": 1, "max": 9410, "std": 622.85, "mod": 200 }, "geometry": { "type": "Point", "coordinates": [ -66.51207, 17.8849 ] } },
{ "type": "Feature", "properties": { "len": 47261, "sum": 36104744, "avg": 763, "min": 1, "max": 9410, "std": 641.47, "mod": 200 }, "geometry": { "type": "Point", "coordinates": [ -65.76207, 18.31795 ] } }
]
}
