{
"type": "FeatureCollection",
"name": "nc-5",
"crs": { "type": "name", "properties": { "name": "urn:ogc:def:crs:OGC:1.3:CRS84" } },
"features": [
{ "type": "Feature", "properties": { "len": 718287, "sum": 416203579, "avg": 579, "min": 1, "max": 59734 }, "geometry": { "type": "Point", "coordinates": [ -84.65484, 33.92666 ] } },
{ "type": "Feature", "properties": { "len": 4482759, "sum": 13411579124, "avg": 2991, "min": 1, "max": 99319 }, "geometry": { "type": "Point", "coordinates": [ -80.90481, 36.09881 ] } },
{ "type": "Feature", "properties": { "len": 5029558, "sum": 11089629368, "avg": 2204, "min": 1, "max": 99501 }, "geometry": { "type": "Point", "coordinates": [ -77.15484, 33.92666 ] } }
]
}
