{
"type": "FeatureCollection",
"name": "data",
"crs": { "type": "name", "properties": { "name": "urn:ogc:def:crs:OGC:1.3:CRS84" } },
"features": [
{ "type": "Feature", "properties": { "len": 8171, "sum": 36606975, "avg": 4480, "min": 1, "max": 20601 }, "geometry": { "type": "Point", "coordinates": [ -88.16442, 37.77563 ] } },
{ "type": "Feature", "properties": { "len": 8171, "sum": 36606975, "avg": 4480, "min": 1, "max": 20601 }, "geometry": { "type": "Point", "coordinates": [ -88.16442, 38.64178 ] } },
{ "type": "Feature", "properties": { "len": 255678, "sum": 853978836, "avg": 3340, "min": 1, "max": 75000 }, "geometry": { "type": "Point", "coordinates": [ -87.41442, 38.2087 ] } },
{ "type": "Feature", "properties": { "len": 129113, "sum": 397081235, "avg": 3075, "min": 1, "max": 75000 }, "geometry": { "type": "Point", "coordinates": [ -87.41442, 39.07485 ] } },
{ "type": "Feature", "properties": { "len": 143545, "sum": 420119029, "avg": 2926, "min": 1, "max": 99101 }, "geometry": { "type": "Point", "coordinates": [ -87.41442, 39.94101 ] } },
{ "type": "Feature", "properties": { "len": 402141, "sum": 1595878245, "avg": 3968, "min": 1, "max": 99101 }, "geometry": { "type": "Point", "coordinates": [ -87.41442, 40.80716 ] } },
{ "type": "Feature", "properties": { "len": 430146, "sum": 1840515641, "avg": 4278, "min": 1, "max": 51802 }, "geometry": { "type": "Point", "coordinates": [ -87.41442, 41.67332 ] } },
{ "type": "Feature", "properties": { "len": 44544, "sum": 200251669, "avg": 4495, "min": 1, "max": 29076 }, "geometry": { "type": "Point", "coordinates": [ -86.66442, 37.77563 ] } },
{ "type": "Feature", "properties": { "len": 182423, "sum": 617528989, "avg": 3385, "min": 1, "max": 29076 }, "geometry": { "type": "Point", "coordinates": [ -86.66442, 38.64178 ] } },
{ "type": "Feature", "properties": { "len": 450268, "sum": 1939722941, "avg": 4307, "min": 1, "max": 69810 }, "geometry": { "type": "Point", "coordinates": [ -86.66442, 39.50793 ] } },
{ "type": "Feature", "properties": { "len": 487101, "sum": 2012134900, "avg": 4130, "min": 1, "max": 99101 }, "geometry": { "type": "Point", "coordinates": [ -86.66442, 40.37408 ] } },
{ "type": "Feature", "properties": { "len": 393305, "sum": 2892348029, "avg": 7353, "min": 1, "max": 72983 }, "geometry": { "type": "Point", "coordinates": [ -86.66442, 41.24024 ] } },
{ "type": "Feature", "properties": { "len": 143099, "sum": 510461515, "avg": 3567, "min": 1, "max": 47141 }, "geometry": { "type": "Point", "coordinates": [ -85.91442, 38.2087 ] } },
{ "type": "Feature", "properties": { "len": 431544, "sum": 1660571244, "avg": 3847, "min": 1, "max": 47141 }, "geometry": { "type": "Point", "coordinates": [ -85.91442, 39.07485 ] } },
{ "type": "Feature", "properties": { "len": 1425912, "sum": 7212653833, "avg": 5058, "min": 1, "max": 84685 }, "geometry": { "type": "Point", "coordinates": [ -85.91442, 39.94101 ] } },
{ "type": "Feature", "properties": { "len": 320600, "sum": 1449019495, "avg": 4519, "min": 1, "max": 84685 }, "geometry": { "type": "Point", "coordinates": [ -85.91442, 40.80716 ] } },
{ "type": "Feature", "properties": { "len": 377163, "sum": 4533389199, "avg": 12019, "min": 1, "max": 72990 }, "geometry": { "type": "Point", "coordinates": [ -85.91442, 41.67332 ] } },
{ "type": "Feature", "properties": { "len": 69022, "sum": 425635292, "avg": 6166, "min": 1, "max": 29997 }, "geometry": { "type": "Point", "coordinates": [ -85.16442, 38.64178 ] } },
{ "type": "Feature", "properties": { "len": 182321, "sum": 722332704, "avg": 3961, "min": 1, "max": 80332 }, "geometry": { "type": "Point", "coordinates": [ -85.16442, 39.50793 ] } },
{ "type": "Feature", "properties": { "len": 569123, "sum": 2118759963, "avg": 3722, "min": 1, "max": 85010 }, "geometry": { "type": "Point", "coordinates": [ -85.16442, 40.37408 ] } },
{ "type": "Feature", "properties": { "len": 469398, "sum": 1975875851, "avg": 4209, "min": 1, "max": 57700 }, "geometry": { "type": "Point", "coordinates": [ -85.16442, 41.24024 ] } }
]
}
